{
  "core_signals": [
    {
      "amount": 1033349011456.0,
      "close": 4085.078,
      "composite_score": 67.75,
      "composite_signal": 5,
      "cumulative_ratio": 1.01,
      "down_count": 1319,
      "high": 4086.638,
      "kdj_signal": 1,
      "low": 4062.133,
      "ma_signal": 2,
      "macd_acceleration_ratio": "31.000",
      "macd_signal": 2,
      "name": "上证指数",
      "open": 4075.846,
      "predicted_amount": 1012125073012.55,
      "rise": 0.07,
      "rise_change_3d": "0.730",
      "rsi_signal": 1,
      "symbol": "SH000001",
      "time": "Tue, 21 Apr 2026 15:00:00 GMT",
      "up_count": 969,
      "up_ratio": 42.35
    },
    {
      "amount": 1375194578944.0,
      "close": 14982.148,
      "composite_score": 67.75,
      "composite_signal": 5,
      "cumulative_ratio": 0.98,
      "down_count": 1875,
      "high": 15017.766,
      "kdj_signal": 1,
      "low": 14774.091,
      "ma_signal": 2,
      "macd_acceleration_ratio": "54.000",
      "macd_signal": 2,
      "name": "深证成指",
      "open": 14920.399,
      "predicted_amount": 1355648480260.92,
      "rise": 0.1,
      "rise_change_3d": "1.260",
      "rsi_signal": -2,
      "symbol": "SZ399001",
      "time": "Tue, 21 Apr 2026 15:00:00 GMT",
      "up_count": 977,
      "up_ratio": 34.26
    },
    {
      "amount": 637778526208.0,
      "close": 3688.939,
      "composite_score": 70.75,
      "composite_signal": 5,
      "cumulative_ratio": 0.95,
      "down_count": 928,
      "high": 3695.742,
      "kdj_signal": 1,
      "low": 3619.485,
      "ma_signal": 2,
      "macd_acceleration_ratio": "67.000",
      "macd_signal": 2,
      "name": "创业板指",
      "open": 3662.259,
      "predicted_amount": 627088220047.28,
      "rise": 0.31,
      "rise_change_3d": "1.730",
      "rsi_signal": -2,
      "symbol": "SZ399006",
      "time": "Tue, 21 Apr 2026 15:00:00 GMT",
      "up_count": 447,
      "up_ratio": 32.51
    },
    {
      "amount": 282348381184.0,
      "close": 1842.374,
      "composite_score": 64.75,
      "composite_signal": 5,
      "cumulative_ratio": 0.99,
      "down_count": 384,
      "high": 1849.513,
      "kdj_signal": 1,
      "low": 1822.248,
      "ma_signal": 2,
      "macd_acceleration_ratio": "67.000",
      "macd_signal": 2,
      "name": "科创综指",
      "open": 1848.746,
      "predicted_amount": 280096304710.06,
      "rise": -0.81,
      "rise_change_3d": "0.690",
      "rsi_signal": 1,
      "symbol": "SH000680",
      "time": "Tue, 21 Apr 2026 15:00:00 GMT",
      "up_count": 215,
      "up_ratio": 35.89
    }
  ],
  "large_cap_signals": [
    {
      "amount": 119509381760.0,
      "close": 2932.072,
      "composite_score": 56.0,
      "composite_signal": 4,
      "cumulative_ratio": 0.91,
      "down_count": 28,
      "high": 2937.419,
      "kdj_signal": 1,
      "low": 2920.284,
      "ma_signal": 2,
      "macd_acceleration_ratio": "25.000",
      "macd_signal": 1,
      "name": "上证50",
      "open": 2931.611,
      "predicted_amount": 119398314478.16,
      "rise": -0.05,
      "rise_change_3d": "-0.260",
      "rsi_signal": 1,
      "symbol": "SH000016",
      "time": "Tue, 21 Apr 2026 15:00:00 GMT",
      "up_count": 20,
      "up_ratio": 41.67
    },
    {
      "amount": 580407998464.0,
      "close": 4767.996,
      "composite_score": 67.75,
      "composite_signal": 5,
      "cumulative_ratio": 0.97,
      "down_count": 170,
      "high": 4776.826,
      "kdj_signal": 1,
      "low": 4722.007,
      "ma_signal": 2,
      "macd_acceleration_ratio": "36.000",
      "macd_signal": 2,
      "name": "沪深300",
      "open": 4750.515,
      "predicted_amount": 581718398739.45,
      "rise": 0.22,
      "rise_change_3d": "0.660",
      "rsi_signal": 1,
      "symbol": "SH000300",
      "time": "Tue, 21 Apr 2026 15:00:00 GMT",
      "up_count": 121,
      "up_ratio": 41.58
    },
    {
      "amount": 321492642048.0,
      "close": 4662.232,
      "composite_score": 67.75,
      "composite_signal": 5,
      "cumulative_ratio": 0.95,
      "down_count": 52,
      "high": 4670.666,
      "kdj_signal": 1,
      "low": 4604.777,
      "ma_signal": 2,
      "macd_acceleration_ratio": "39.000",
      "macd_signal": 2,
      "name": "中证100",
      "open": 4644.978,
      "predicted_amount": 327789721431.96,
      "rise": 0.34,
      "rise_change_3d": "0.360",
      "rsi_signal": 1,
      "symbol": "SZ399903",
      "time": "Tue, 21 Apr 2026 15:00:00 GMT",
      "up_count": 44,
      "up_ratio": 45.83
    },
    {
      "amount": 1021931113472.0,
      "close": 5369.478,
      "composite_score": 67.75,
      "composite_signal": 5,
      "cumulative_ratio": 0.96,
      "down_count": 0,
      "high": 5378.381,
      "kdj_signal": 1,
      "low": 5317.54,
      "ma_signal": 2,
      "macd_acceleration_ratio": "41.000",
      "macd_signal": 2,
      "name": "中证800",
      "open": 5354.132,
      "predicted_amount": 1018232670329.86,
      "rise": 0.09,
      "rise_change_3d": "0.790",
      "rsi_signal": 1,
      "symbol": "SH000906",
      "time": "Tue, 21 Apr 2026 15:00:00 GMT",
      "up_count": 0,
      "up_ratio": 0.0
    }
  ],
  "mid_small_cap_signals": [
    {
      "amount": 182537362688.0,
      "close": 9774.274,
      "composite_score": 67.75,
      "composite_signal": 5,
      "cumulative_ratio": 0.93,
      "down_count": 29,
      "high": 9794.272,
      "kdj_signal": 1,
      "low": 9633.471,
      "ma_signal": 2,
      "macd_acceleration_ratio": "52.000",
      "macd_signal": 2,
      "name": "深证50",
      "open": 9736.238,
      "predicted_amount": 189937973515.66,
      "rise": 0.17,
      "rise_change_3d": "1.380",
      "rsi_signal": -2,
      "symbol": "SZ399850",
      "time": "Tue, 21 Apr 2026 15:00:00 GMT",
      "up_count": 20,
      "up_ratio": 40.82
    },
    {
      "amount": 288289352960.0,
      "close": 6376.294,
      "composite_score": 67.75,
      "composite_signal": 5,
      "cumulative_ratio": 0.99,
      "down_count": 1875,
      "high": 6392.341,
      "kdj_signal": 1,
      "low": 6273.078,
      "ma_signal": 2,
      "macd_acceleration_ratio": "50.000",
      "macd_signal": 2,
      "name": "深证100",
      "open": 6335.613,
      "predicted_amount": 292849205653.26,
      "rise": 0.41,
      "rise_change_3d": "1.350",
      "rsi_signal": -2,
      "symbol": "SZ399330",
      "time": "Tue, 21 Apr 2026 15:00:00 GMT",
      "up_count": 977,
      "up_ratio": 34.26
    },
    {
      "amount": 441523122176.0,
      "close": 8270.324,
      "composite_score": 64.75,
      "composite_signal": 5,
      "cumulative_ratio": 0.96,
      "down_count": 284,
      "high": 8281.32,
      "kdj_signal": 1,
      "low": 8189.758,
      "ma_signal": 2,
      "macd_acceleration_ratio": "53.000",
      "macd_signal": 2,
      "name": "中证500",
      "open": 8263.379,
      "predicted_amount": 436610768283.97,
      "rise": -0.24,
      "rise_change_3d": "1.100",
      "rsi_signal": 1,
      "symbol": "SH000905",
      "time": "Tue, 21 Apr 2026 15:00:00 GMT",
      "up_count": 207,
      "up_ratio": 42.16
    },
    {
      "amount": 521902185984.0,
      "close": 8351.163,
      "composite_score": 64.75,
      "composite_signal": 5,
      "cumulative_ratio": 0.99,
      "down_count": 591,
      "high": 8358.124,
      "kdj_signal": 1,
      "low": 8270.16,
      "ma_signal": 2,
      "macd_acceleration_ratio": "54.000",
      "macd_signal": 2,
      "name": "中证1000",
      "open": 8331.592,
      "predicted_amount": 514254525929.27,
      "rise": -0.08,
      "rise_change_3d": "1.440",
      "rsi_signal": 1,
      "symbol": "SH000852",
      "time": "Tue, 21 Apr 2026 15:00:00 GMT",
      "up_count": 389,
      "up_ratio": 39.69
    },
    {
      "amount": 68696504448.0,
      "close": 1684.68,
      "composite_score": 70.75,
      "composite_signal": 5,
      "cumulative_ratio": 0.96,
      "down_count": 62,
      "high": 1689.0,
      "kdj_signal": 1,
      "low": 1658.849,
      "ma_signal": 2,
      "macd_acceleration_ratio": "67.000",
      "macd_signal": 2,
      "name": "科创100",
      "open": 1677.404,
      "predicted_amount": 68917341944.26,
      "rise": 0.12,
      "rise_change_3d": "1.770",
      "rsi_signal": -2,
      "symbol": "SH000698",
      "time": "Tue, 21 Apr 2026 15:00:00 GMT",
      "up_count": 37,
      "up_ratio": 37.37
    },
    {
      "amount": 80219231424.0,
      "close": 1426.672,
      "composite_score": 61.75,
      "composite_signal": 5,
      "cumulative_ratio": 0.89,
      "down_count": 384,
      "high": 1445.539,
      "kdj_signal": 1,
      "low": 1415.6,
      "ma_signal": 2,
      "macd_acceleration_ratio": "73.000",
      "macd_signal": 2,
      "name": "科创50",
      "open": 1445.204,
      "predicted_amount": 81445330748.63,
      "rise": -1.64,
      "rise_change_3d": "0.310",
      "rsi_signal": 1,
      "symbol": "SH000688",
      "time": "Tue, 21 Apr 2026 15:00:00 GMT",
      "up_count": 215,
      "up_ratio": 35.89
    },
    {
      "amount": 215520957696.0,
      "close": 3950.077,
      "composite_score": 70.75,
      "composite_signal": 5,
      "cumulative_ratio": 0.93,
      "down_count": 0,
      "high": 3958.016,
      "kdj_signal": 1,
      "low": 3866.397,
      "ma_signal": 2,
      "macd_acceleration_ratio": "73.000",
      "macd_signal": 2,
      "name": "创业50",
      "open": 3914.329,
      "predicted_amount": 218369274813.98,
      "rise": 0.45,
      "rise_change_3d": "2.180",
      "rsi_signal": -2,
      "symbol": "SZ399673",
      "time": "Tue, 21 Apr 2026 15:00:00 GMT",
      "up_count": 0,
      "up_ratio": 0.0
    },
    {
      "amount": 72464519936.0,
      "close": 1612.022,
      "composite_score": 70.75,
      "composite_signal": 5,
      "cumulative_ratio": 0.98,
      "down_count": 0,
      "high": 1614.248,
      "kdj_signal": 1,
      "low": 1579.298,
      "ma_signal": 2,
      "macd_acceleration_ratio": "62.000",
      "macd_signal": 2,
      "name": "科创200",
      "open": 1594.015,
      "predicted_amount": 73962094763.39,
      "rise": 0.63,
      "rise_change_3d": "1.660",
      "rsi_signal": -2,
      "symbol": "SH000699",
      "time": "Tue, 21 Apr 2026 15:00:00 GMT",
      "up_count": 0,
      "up_ratio": 0.0
    },
    {
      "amount": 128396921472.0,
      "close": 4879.514,
      "composite_score": 67.75,
      "composite_signal": 5,
      "cumulative_ratio": 0.9,
      "down_count": 0,
      "high": 4881.893,
      "kdj_signal": 1,
      "low": 4830.079,
      "ma_signal": 2,
      "macd_acceleration_ratio": "67.000",
      "macd_signal": 2,
      "name": "创业200",
      "open": 4874.746,
      "predicted_amount": 127667613319.68,
      "rise": -0.34,
      "rise_change_3d": "1.540",
      "rsi_signal": 1,
      "symbol": "SZ399019",
      "time": "Tue, 21 Apr 2026 15:00:00 GMT",
      "up_count": 0,
      "up_ratio": 0.0
    },
    {
      "amount": 814586476544.0,
      "close": 10996.894,
      "composite_score": 64.75,
      "composite_signal": 5,
      "cumulative_ratio": 1.02,
      "down_count": 0,
      "high": 11001.288,
      "kdj_signal": 1,
      "low": 10886.307,
      "ma_signal": 2,
      "macd_acceleration_ratio": "55.000",
      "macd_signal": 2,
      "name": "国证2000",
      "open": 10965.364,
      "predicted_amount": 790587800817.19,
      "rise": -0.1,
      "rise_change_3d": "1.430",
      "rsi_signal": 1,
      "symbol": "SZ399303",
      "time": "Tue, 21 Apr 2026 15:00:00 GMT",
      "up_count": 0,
      "up_ratio": 0.0
    },
    {
      "amount": 186411948416.0,
      "close": 9130.318,
      "composite_score": 67.75,
      "composite_signal": 5,
      "cumulative_ratio": 1.03,
      "down_count": 0,
      "high": 9159.713,
      "kdj_signal": 1,
      "low": 9004.108,
      "ma_signal": 2,
      "macd_acceleration_ratio": "51.000",
      "macd_signal": 2,
      "name": "中小100",
      "open": 9097.686,
      "predicted_amount": 187315194161.23,
      "rise": 0.24,
      "rise_change_3d": "1.250",
      "rsi_signal": -2,
      "symbol": "SZ399005",
      "time": "Tue, 21 Apr 2026 15:00:00 GMT",
      "up_count": 0,
      "up_ratio": 0.0
    }
  ],
  "timestamp": "2026-04-21T15:05:32.116119"
}